app/__init__.py
app/auth.py
app/db.py
app/schema.sql
app/settings.py
app/tool.py
app/utils.py
app/static/css/base.css
app/static/css/bootstrap.css
app/static/css/bootstrap.css.map
app/static/css/bootstrap.js.map
app/static/css/jquery.datetimepicker.css
app/static/css/jquery.datetimepicker.min.css
app/static/js/alerts.js
app/static/js/axios.min.js
app/static/js/axios.min.map
app/static/js/bootstrap.bundle.min.js
app/static/js/bootstrap.bundle.min.js.map
app/static/js/bootstrap.js
app/static/js/bootstrap.js.map
app/static/js/feather.min.js
app/static/js/feather.min.js.map
app/static/js/jquery-3.5.1.js
app/static/js/jquery.datetimepicker.full.min.js
app/static/js/vue.js
app/static/pic/CL1.jpg
app/static/pic/adam.jpg
app/static/pic/bootstrap-solid.svg
app/static/pic/home-bg.jpg
app/static/pic/logo.png
app/templates/base.html
app/templates/index.html
app/templates/404/page_not_found.html
app/templates/auth/login.html
app/templates/auth/register.html
app/templates/auth/users.html
app/templates/log/log.html
app/templates/modbus/modbus_index.html
app/templates/modbus/modbus_show.html
modbus_config_tools-1.0.1.dist-info/LICENSE
modbus_config_tools-1.0.1.dist-info/METADATA
modbus_config_tools-1.0.1.dist-info/WHEEL
modbus_config_tools-1.0.1.dist-info/top_level.txt
modbus_config_tools-1.0.1.dist-info/RECORD
